{
  "soc_verlauf": [
    {
      "soc": 45,
      "zeit": "2026-05-01T04:00:45.910389"
    },
    {
      "soc": 45,
      "zeit": "2026-05-01T04:05:30.163300"
    },
    {
      "soc": 45,
      "zeit": "2026-05-01T04:10:32.692738"
    },
    {
      "soc": 44,
      "zeit": "2026-05-01T04:15:31.446975"
    }
  ],
  "schaltungen_heute": {
    "datum": "2026-05-01",
    "ein_3kw": 0,
    "aus_3kw": 0,
    "ein_6kw": 0,
    "aus_6kw": 0
  },
  "heizstab_3kw_ein": false,
  "modus_3kw": null,
  "einschalt_pending_3kw": null,
  "soc_abschaltung_3kw": false,
  "letzte_schaltzeit": "2026-04-30T16:31:26.179869",
  "letzte_aktualisierung": "2026-05-01T04:15:43.260669",
  "ausschalt_pending_3kw": null,
  "tages_datum": "2026-05-01",
  "tages_verlauf": [
    {
      "zeit": "06:00",
      "soc": 45,
      "pv_w": 16,
      "haus_w": 375,
      "einspeisung_w": 7,
      "netzbezug_w": 0,
      "bat_laden_w": 0,
      "bat_entladen_w": 366,
      "ueberschuss_w": 0
    },
    {
      "zeit": "06:05",
      "soc": 45,
      "pv_w": 44,
      "haus_w": 588,
      "einspeisung_w": 0,
      "netzbezug_w": 1,
      "bat_laden_w": 0,
      "bat_entladen_w": 543,
      "ueberschuss_w": 0
    },
    {
      "zeit": "06:10",
      "soc": 45,
      "pv_w": 49,
      "haus_w": 356,
      "einspeisung_w": 10,
      "netzbezug_w": 0,
      "bat_laden_w": 0,
      "bat_entladen_w": 317,
      "ueberschuss_w": 0
    },
    {
      "zeit": "06:15",
      "soc": 44,
      "pv_w": 71,
      "haus_w": 426,
      "einspeisung_w": 0,
      "netzbezug_w": 17,
      "bat_laden_w": 0,
      "bat_entladen_w": 338,
      "ueberschuss_w": 0
    }
  ],
  "schaltpunkte_heute": [],
  "tages_energie_isolarcloud": {
    "pv_kwh": 0.0,
    "einspeisung_kwh": 0.0,
    "netzbezug_kwh": 0.0,
    "bat_laden_kwh": 0.0,
    "bat_entladen_kwh": 3.0,
    "haus_kwh": 3.0
  },
  "morgenreport_datum": "2026-04-30",
  "abendreport_datum": "2026-04-30",
  "einschalt_pending_6kw": null,
  "einschalt_schwelle_3kw": null,
  "nach_ausschalt_sperre_3kw": false,
  "heizstab_6kw_ein": false,
  "modus_6kw": null,
  "soc_abschaltung_6kw": false,
  "einschalt_schwelle_6kw": null,
  "nach_ausschalt_sperre_6kw": false,
  "manuell_sperre_bis": null,
  "abschalt_pruefung_datum": "2026-04-30",
  "ausschalt_pending_6kw": null,
  "batterie_war_voll": false,
  "manuell_sperre_6kw_bis": null,
  "manuell_sperre_3kw_bis": null,
  "laderate_verlauf": [
    {
      "zeit": "06:05",
      "soc": 45,
      "ueberschuss": 0,
      "laderate": null,
      "n_punkte": 2
    },
    {
      "zeit": "06:10",
      "soc": 45,
      "ueberschuss": 0,
      "laderate": 0.0,
      "n_punkte": 3
    },
    {
      "zeit": "06:15",
      "soc": 44,
      "ueberschuss": 0,
      "laderate": -4.1,
      "n_punkte": 4
    }
  ],
  "saisonale_abschaltung_6kw": null,
  "saisonale_abschaltung_3kw": null,
  "thermostat_pause_3kw_bis": null,
  "thermostat_pause_6kw_bis": null
}