{
  "soc_verlauf": [
    {
      "soc": 82,
      "zeit": "2026-04-24T07:05:27.495732"
    },
    {
      "soc": 83,
      "zeit": "2026-04-24T07:10:30.852141"
    },
    {
      "soc": 84,
      "zeit": "2026-04-24T07:15:29.177267"
    },
    {
      "soc": 85,
      "zeit": "2026-04-24T07:20:44.829994"
    },
    {
      "soc": 89,
      "zeit": "2026-04-24T07:26:05.971292"
    },
    {
      "soc": 89,
      "zeit": "2026-04-24T07:30:48.067360"
    },
    {
      "soc": 90,
      "zeit": "2026-04-24T07:35:27.862030"
    },
    {
      "soc": 93,
      "zeit": "2026-04-24T07:40:33.162322"
    },
    {
      "soc": 95,
      "zeit": "2026-04-24T07:45:33.139921"
    },
    {
      "soc": 96,
      "zeit": "2026-04-24T07:50:28.149304"
    },
    {
      "soc": 100,
      "zeit": "2026-04-24T07:55:24.759915"
    },
    {
      "soc": 100,
      "zeit": "2026-04-24T08:00:47.551267"
    }
  ],
  "schaltungen_heute": {
    "datum": "2026-04-24",
    "ein_3kw": 1,
    "aus_3kw": 0,
    "ein_6kw": 0,
    "aus_6kw": 0
  },
  "heizstab_3kw_ein": true,
  "modus_3kw": "NORMAL",
  "einschalt_pending_3kw": null,
  "soc_abschaltung_3kw": false,
  "letzte_schaltzeit": "2026-04-24T06:51:10.786438",
  "letzte_aktualisierung": "2026-04-24T08:00:58.784997",
  "ausschalt_pending_3kw": null,
  "tages_datum": "2026-04-24",
  "tages_verlauf": [
    {
      "zeit": "06:00",
      "soc": 53,
      "pv_w": 0,
      "haus_w": 361,
      "einspeisung_w": 5,
      "netzbezug_w": 0,
      "bat_laden_w": 0,
      "bat_entladen_w": 366,
      "ueberschuss_w": 0
    },
    {
      "zeit": "06:05",
      "soc": 53,
      "pv_w": 0,
      "haus_w": 386,
      "einspeisung_w": 0,
      "netzbezug_w": 9,
      "bat_laden_w": 0,
      "bat_entladen_w": 377,
      "ueberschuss_w": 0
    },
    {
      "zeit": "06:10",
      "soc": 53,
      "pv_w": 2,
      "haus_w": 501,
      "einspeisung_w": 0,
      "netzbezug_w": 13,
      "bat_laden_w": 0,
      "bat_entladen_w": 486,
      "ueberschuss_w": 0
    },
    {
      "zeit": "06:15",
      "soc": 52,
      "pv_w": 22,
      "haus_w": 414,
      "einspeisung_w": 0,
      "netzbezug_w": 2,
      "bat_laden_w": 0,
      "bat_entladen_w": 390,
      "ueberschuss_w": 0
    },
    {
      "zeit": "06:20",
      "soc": 52,
      "pv_w": 50,
      "haus_w": 595,
      "einspeisung_w": 0,
      "netzbezug_w": 1,
      "bat_laden_w": 0,
      "bat_entladen_w": 544,
      "ueberschuss_w": 0
    },
    {
      "zeit": "06:25",
      "soc": 52,
      "pv_w": 79,
      "haus_w": 316,
      "einspeisung_w": 0,
      "netzbezug_w": 21,
      "bat_laden_w": 0,
      "bat_entladen_w": 216,
      "ueberschuss_w": 0
    },
    {
      "zeit": "06:30",
      "soc": 52,
      "pv_w": 119,
      "haus_w": 600,
      "einspeisung_w": 22,
      "netzbezug_w": 0,
      "bat_laden_w": 0,
      "bat_entladen_w": 503,
      "ueberschuss_w": 0
    },
    {
      "zeit": "06:35",
      "soc": 50,
      "pv_w": 172,
      "haus_w": 366,
      "einspeisung_w": 0,
      "netzbezug_w": 11,
      "bat_laden_w": 0,
      "bat_entladen_w": 183,
      "ueberschuss_w": 0
    },
    {
      "zeit": "06:40",
      "soc": 50,
      "pv_w": 697,
      "haus_w": 1214,
      "einspeisung_w": 0,
      "netzbezug_w": 245,
      "bat_laden_w": 0,
      "bat_entladen_w": 272,
      "ueberschuss_w": 0
    },
    {
      "zeit": "06:45",
      "soc": 52,
      "pv_w": 807,
      "haus_w": 580,
      "einspeisung_w": 2,
      "netzbezug_w": 0,
      "bat_laden_w": 225,
      "bat_entladen_w": 0,
      "ueberschuss_w": 227
    },
    {
      "zeit": "06:50",
      "soc": 52,
      "pv_w": 919,
      "haus_w": 368,
      "einspeisung_w": 15,
      "netzbezug_w": 0,
      "bat_laden_w": 536,
      "bat_entladen_w": 0,
      "ueberschuss_w": 551
    },
    {
      "zeit": "06:55",
      "soc": 52,
      "pv_w": 1021,
      "haus_w": 395,
      "einspeisung_w": 0,
      "netzbezug_w": 18,
      "bat_laden_w": 644,
      "bat_entladen_w": 0,
      "ueberschuss_w": 626
    },
    {
      "zeit": "07:00",
      "soc": 52,
      "pv_w": 1146,
      "haus_w": 628,
      "einspeisung_w": 0,
      "netzbezug_w": 4,
      "bat_laden_w": 522,
      "bat_entladen_w": 0,
      "ueberschuss_w": 518
    },
    {
      "zeit": "07:05",
      "soc": 53,
      "pv_w": 1246,
      "haus_w": 431,
      "einspeisung_w": 0,
      "netzbezug_w": 9,
      "bat_laden_w": 824,
      "bat_entladen_w": 0,
      "ueberschuss_w": 815
    },
    {
      "zeit": "07:10",
      "soc": 53,
      "pv_w": 1340,
      "haus_w": 327,
      "einspeisung_w": 0,
      "netzbezug_w": 4,
      "bat_laden_w": 1017,
      "bat_entladen_w": 0,
      "ueberschuss_w": 1013
    },
    {
      "zeit": "07:15",
      "soc": 54,
      "pv_w": 1434,
      "haus_w": 328,
      "einspeisung_w": 0,
      "netzbezug_w": 3,
      "bat_laden_w": 1109,
      "bat_entladen_w": 0,
      "ueberschuss_w": 1106
    },
    {
      "zeit": "07:20",
      "soc": 54,
      "pv_w": 1522,
      "haus_w": 322,
      "einspeisung_w": 15,
      "netzbezug_w": 0,
      "bat_laden_w": 1185,
      "bat_entladen_w": 0,
      "ueberschuss_w": 1200
    },
    {
      "zeit": "07:25",
      "soc": 54,
      "pv_w": 1586,
      "haus_w": 1542,
      "einspeisung_w": 0,
      "netzbezug_w": 533,
      "bat_laden_w": 577,
      "bat_entladen_w": 0,
      "ueberschuss_w": 44
    },
    {
      "zeit": "07:30",
      "soc": 54,
      "pv_w": 1693,
      "haus_w": 2362,
      "einspeisung_w": 0,
      "netzbezug_w": 6,
      "bat_laden_w": 0,
      "bat_entladen_w": 663,
      "ueberschuss_w": 0
    },
    {
      "zeit": "07:35",
      "soc": 54,
      "pv_w": 2352,
      "haus_w": 2373,
      "einspeisung_w": 0,
      "netzbezug_w": 21,
      "bat_laden_w": 0,
      "bat_entladen_w": 0,
      "ueberschuss_w": 0
    },
    {
      "zeit": "07:40",
      "soc": 54,
      "pv_w": 2500,
      "haus_w": 2206,
      "einspeisung_w": 0,
      "netzbezug_w": 5,
      "bat_laden_w": 299,
      "bat_entladen_w": 0,
      "ueberschuss_w": 294
    },
    {
      "zeit": "07:45",
      "soc": 54,
      "pv_w": 3139,
      "haus_w": 2827,
      "einspeisung_w": 0,
      "netzbezug_w": 10,
      "bat_laden_w": 322,
      "bat_entladen_w": 0,
      "ueberschuss_w": 312
    },
    {
      "zeit": "07:50",
      "soc": 54,
      "pv_w": 3341,
      "haus_w": 2651,
      "einspeisung_w": 0,
      "netzbezug_w": 1,
      "bat_laden_w": 691,
      "bat_entladen_w": 0,
      "ueberschuss_w": 690
    },
    {
      "zeit": "07:55",
      "soc": 54,
      "pv_w": 3528,
      "haus_w": 2629,
      "einspeisung_w": 6,
      "netzbezug_w": 0,
      "bat_laden_w": 893,
      "bat_entladen_w": 0,
      "ueberschuss_w": 899
    },
    {
      "zeit": "08:00",
      "soc": 55,
      "pv_w": 3748,
      "haus_w": 2530,
      "einspeisung_w": 0,
      "netzbezug_w": 14,
      "bat_laden_w": 1232,
      "bat_entladen_w": 0,
      "ueberschuss_w": 1218
    },
    {
      "zeit": "08:05",
      "soc": 55,
      "pv_w": 3956,
      "haus_w": 2570,
      "einspeisung_w": 0,
      "netzbezug_w": 18,
      "bat_laden_w": 1404,
      "bat_entladen_w": 0,
      "ueberschuss_w": 1386
    },
    {
      "zeit": "08:10",
      "soc": 57,
      "pv_w": 4115,
      "haus_w": 501,
      "einspeisung_w": 17,
      "netzbezug_w": 0,
      "bat_laden_w": 3597,
      "bat_entladen_w": 0,
      "ueberschuss_w": 3614
    },
    {
      "zeit": "08:15",
      "soc": 58,
      "pv_w": 4330,
      "haus_w": 497,
      "einspeisung_w": 0,
      "netzbezug_w": 9,
      "bat_laden_w": 3842,
      "bat_entladen_w": 0,
      "ueberschuss_w": 3833
    },
    {
      "zeit": "08:20",
      "soc": 60,
      "pv_w": 4576,
      "haus_w": 2363,
      "einspeisung_w": 13,
      "netzbezug_w": 0,
      "bat_laden_w": 2200,
      "bat_entladen_w": 0,
      "ueberschuss_w": 2213
    },
    {
      "zeit": "08:25",
      "soc": 62,
      "pv_w": 4719,
      "haus_w": 439,
      "einspeisung_w": 0,
      "netzbezug_w": 3,
      "bat_laden_w": 4283,
      "bat_entladen_w": 0,
      "ueberschuss_w": 4280
    },
    {
      "zeit": "08:30",
      "soc": 64,
      "pv_w": 4965,
      "haus_w": 525,
      "einspeisung_w": 0,
      "netzbezug_w": 9,
      "bat_laden_w": 4449,
      "bat_entladen_w": 0,
      "ueberschuss_w": 4440
    },
    {
      "zeit": "08:35",
      "soc": 66,
      "pv_w": 5127,
      "haus_w": 448,
      "einspeisung_w": 0,
      "netzbezug_w": 17,
      "bat_laden_w": 4696,
      "bat_entladen_w": 0,
      "ueberschuss_w": 4679
    },
    {
      "zeit": "08:40",
      "soc": 69,
      "pv_w": 5298,
      "haus_w": 452,
      "einspeisung_w": 0,
      "netzbezug_w": 2,
      "bat_laden_w": 4848,
      "bat_entladen_w": 0,
      "ueberschuss_w": 4846
    },
    {
      "zeit": "08:45",
      "soc": 72,
      "pv_w": 5458,
      "haus_w": 569,
      "einspeisung_w": 16,
      "netzbezug_w": 0,
      "bat_laden_w": 4873,
      "bat_entladen_w": 0,
      "ueberschuss_w": 4889
    },
    {
      "zeit": "08:50",
      "soc": 75,
      "pv_w": 5610,
      "haus_w": 612,
      "einspeisung_w": 0,
      "netzbezug_w": 14,
      "bat_laden_w": 5012,
      "bat_entladen_w": 0,
      "ueberschuss_w": 4998
    },
    {
      "zeit": "08:55",
      "soc": 77,
      "pv_w": 5762,
      "haus_w": 499,
      "einspeisung_w": 5,
      "netzbezug_w": 0,
      "bat_laden_w": 5258,
      "bat_entladen_w": 0,
      "ueberschuss_w": 5263
    },
    {
      "zeit": "09:00",
      "soc": 80,
      "pv_w": 5918,
      "haus_w": 793,
      "einspeisung_w": 0,
      "netzbezug_w": 0,
      "bat_laden_w": 5125,
      "bat_entladen_w": 0,
      "ueberschuss_w": 5125
    },
    {
      "zeit": "09:05",
      "soc": 82,
      "pv_w": 6085,
      "haus_w": 3294,
      "einspeisung_w": 0,
      "netzbezug_w": 6,
      "bat_laden_w": 2797,
      "bat_entladen_w": 0,
      "ueberschuss_w": 2791
    },
    {
      "zeit": "09:10",
      "soc": 83,
      "pv_w": 6226,
      "haus_w": 3288,
      "einspeisung_w": 0,
      "netzbezug_w": 16,
      "bat_laden_w": 2954,
      "bat_entladen_w": 0,
      "ueberschuss_w": 2938
    },
    {
      "zeit": "09:15",
      "soc": 84,
      "pv_w": 6265,
      "haus_w": 3711,
      "einspeisung_w": 0,
      "netzbezug_w": 62,
      "bat_laden_w": 2616,
      "bat_entladen_w": 0,
      "ueberschuss_w": 2554
    },
    {
      "zeit": "09:20",
      "soc": 85,
      "pv_w": 6515,
      "haus_w": 4061,
      "einspeisung_w": 0,
      "netzbezug_w": 3,
      "bat_laden_w": 2457,
      "bat_entladen_w": 0,
      "ueberschuss_w": 2454
    },
    {
      "zeit": "09:26",
      "soc": 89,
      "pv_w": 6797,
      "haus_w": 3723,
      "einspeisung_w": 5,
      "netzbezug_w": 0,
      "bat_laden_w": 3069,
      "bat_entladen_w": 0,
      "ueberschuss_w": 3074
    },
    {
      "zeit": "09:30",
      "soc": 89,
      "pv_w": 6797,
      "haus_w": 3723,
      "einspeisung_w": 5,
      "netzbezug_w": 0,
      "bat_laden_w": 3069,
      "bat_entladen_w": 0,
      "ueberschuss_w": 3074
    },
    {
      "zeit": "09:35",
      "soc": 90,
      "pv_w": 6936,
      "haus_w": 3803,
      "einspeisung_w": 0,
      "netzbezug_w": 5,
      "bat_laden_w": 3138,
      "bat_entladen_w": 0,
      "ueberschuss_w": 3133
    },
    {
      "zeit": "09:40",
      "soc": 93,
      "pv_w": 7056,
      "haus_w": 3772,
      "einspeisung_w": 0,
      "netzbezug_w": 16,
      "bat_laden_w": 3300,
      "bat_entladen_w": 0,
      "ueberschuss_w": 3284
    },
    {
      "zeit": "09:45",
      "soc": 95,
      "pv_w": 7207,
      "haus_w": 3780,
      "einspeisung_w": 14,
      "netzbezug_w": 0,
      "bat_laden_w": 3413,
      "bat_entladen_w": 0,
      "ueberschuss_w": 3427
    },
    {
      "zeit": "09:50",
      "soc": 96,
      "pv_w": 7375,
      "haus_w": 3795,
      "einspeisung_w": 0,
      "netzbezug_w": 3,
      "bat_laden_w": 3583,
      "bat_entladen_w": 0,
      "ueberschuss_w": 3580
    },
    {
      "zeit": "09:55",
      "soc": 100,
      "pv_w": 7518,
      "haus_w": 3830,
      "einspeisung_w": 3688,
      "netzbezug_w": 0,
      "bat_laden_w": 0,
      "bat_entladen_w": 0,
      "ueberschuss_w": 3688
    },
    {
      "zeit": "10:00",
      "soc": 100,
      "pv_w": 7681,
      "haus_w": 3863,
      "einspeisung_w": 3818,
      "netzbezug_w": 0,
      "bat_laden_w": 0,
      "bat_entladen_w": 0,
      "ueberschuss_w": 3818
    }
  ],
  "schaltpunkte_heute": [
    {
      "zeit": "08:50",
      "geraet": "3kw",
      "aktion": "EIN",
      "soc": 75,
      "pv_w": 5610,
      "modus": "NORMAL"
    }
  ],
  "tages_energie_isolarcloud": {
    "pv_kwh": 14.0,
    "einspeisung_kwh": 0.5,
    "netzbezug_kwh": 0.0,
    "bat_laden_kwh": 7.4,
    "bat_entladen_kwh": 2.8,
    "haus_kwh": 8.9
  },
  "morgenreport_datum": "2026-04-24",
  "abendreport_datum": "2026-04-23",
  "einschalt_pending_6kw": "2026-04-24T07:55:35.781188",
  "einschalt_schwelle_3kw": 45,
  "nach_ausschalt_sperre_3kw": false,
  "heizstab_6kw_ein": false,
  "modus_6kw": null,
  "soc_abschaltung_6kw": false,
  "einschalt_schwelle_6kw": null,
  "nach_ausschalt_sperre_6kw": false,
  "manuell_sperre_bis": null,
  "abschalt_pruefung_datum": "2026-04-23",
  "ausschalt_pending_6kw": null,
  "batterie_war_voll": true,
  "manuell_sperre_6kw_bis": null
}